robo_ai/__init__.py
robo_ai/robo_ai.py
robo_ai/exception/__init__.py
robo_ai/exception/api_error.py
robo_ai/exception/invalid_credentials_error.py
robo_ai/exception/invalid_token_error.py
robo_ai/exception/not_authorized_error.py
robo_ai/exception/not_found_error.py
robo_ai/model/__init__.py
robo_ai/model/base_response.py
robo_ai/model/config.py
robo_ai/model/paginated_base_response.py
robo_ai/model/session.py
robo_ai/model/assistant/__init__.py
robo_ai/model/assistant/assistant.py
robo_ai/model/assistant/assistant_list_response.py
robo_ai/model/assistant/assistant_param.py
robo_ai/model/assistant/assistant_response.py
robo_ai/model/assistant_runtime/__init__.py
robo_ai/model/assistant_runtime/assistant_runtime.py
robo_ai/model/assistant_runtime/assistant_runtime_logs.py
robo_ai/model/assistant_runtime/assistant_runtime_logs_response.py
robo_ai/model/assistant_runtime/assistant_runtime_response.py
robo_ai/model/assistant_runtime/assistant_runtime_status.py
robo_ai/model/auth/__init__.py
robo_ai/model/auth/access_info.py
robo_ai/model/auth/access_token.py
robo_ai/resources/__init__.py
robo_ai/resources/assistant_runtimes.py
robo_ai/resources/assistants.py
robo_ai/resources/base_resource.py
robo_ai/resources/client_resource.py
robo_ai/resources/oauth.py
robo_ai-0.1.1.dist-info/WHEEL
robo_ai-0.1.1.dist-info/METADATA
robo_ai-0.1.1.dist-info/RECORD
