Metadata-Version: 2.1
Name: robo_ai
Version: 0.1.1
Summary: An SDK for ROBO.AI
Home-page: UNKNOWN
License: UNKNOWN
Author: ROBO.AI
Author-email: info@robo-ai.com
Requires-Dist: requests >=2.23.0
Requires-Dist: cattrs >=1.0.0
Requires-Dist: attrs >=19.3.0
Requires-Dist: requests-toolbelt >=0.9.1
Requires-Dist: configparser; python_version >= '3.6'
